adstxt/__init__.py
adstxt/adstxt.py
adstxt/cli.py
adstxt/validators.py
adstxt-0.1.0.dist-info/DESCRIPTION.rst
adstxt-0.1.0.dist-info/METADATA
adstxt-0.1.0.dist-info/RECORD
adstxt-0.1.0.dist-info/WHEEL
adstxt-0.1.0.dist-info/entry_points.txt
adstxt-0.1.0.dist-info/metadata.json
adstxt-0.1.0.dist-info/top_level.txt
