Metadata-Version: 2.0
Name: adstxt
Version: 0.1.0
Summary: Validate ads.txt files against the official ads.txt specs.
Home-page: https://github.com/maxrodrigo/adstxt
Author: Max Rodrigo
Author-email: contact@maxrodrigo.com
License: MIT license
Keywords: adstxt ads.txt validation GAM IAB
Platform: UNKNOWN
Classifier: Development Status :: 2 - Pre-Alpha
Classifier: Intended Audience :: Developers
Classifier: License :: OSI Approved :: MIT License
Classifier: Natural Language :: English
Classifier: Programming Language :: Python :: 2
Classifier: Programming Language :: Python :: 2.7
Classifier: Programming Language :: Python :: 3
Classifier: Programming Language :: Python :: 3.4
Classifier: Programming Language :: Python :: 3.5
Classifier: Programming Language :: Python :: 3.6
Classifier: Programming Language :: Python :: 3.7
Requires-Dist: Click (>=6.0)
